pybuildhelper/__init__.py
pybuildhelper/build_helper.py
pybuildhelper-0.0.2.dist-info/LICENSE
pybuildhelper-0.0.2.dist-info/METADATA
pybuildhelper-0.0.2.dist-info/WHEEL
pybuildhelper-0.0.2.dist-info/top_level.txt
pybuildhelper-0.0.2.dist-info/RECORD
