Metadata-Version: 2.2
Name: pybuildhelper
Version: 0.0.2
Summary: A python build helper library to compile (obfuscate) and pack Python files using Cython and PyInstaller
Home-page: https://github.com/xfally/pybuildhelper
Author: pax
Author-email: coolwinding@foxmail.com
Classifier: Programming Language :: Python :: 3
Classifier: License :: OSI Approved :: MIT License
Classifier: Operating System :: OS Independent
Requires-Python: >=3.8
License-File: LICENSE
Requires-Dist: Cython
Requires-Dist: pyinstaller
Requires-Dist: setuptools
Dynamic: author
Dynamic: author-email
Dynamic: classifier
Dynamic: description
Dynamic: description-content-type
Dynamic: home-page
Dynamic: requires-dist
Dynamic: requires-python
Dynamic: summary
